TrackerGG/__init__.py
TrackerGG/client.py
TrackerGG/utils.py
TrackerGG/HTTPClients/__init__.py
TrackerGG/HTTPClients/abstract_http_client.py
TrackerGG/HTTPClients/aiohttp_client.py
TrackerGG/HTTPClients/httpclient.py
TrackerGG/HTTPClients/httpx_client.py
TrackerGG/Models/__init__.py
TrackerGG/Models/Apex/__init__.py
TrackerGG/Models/Apex/apex_profile.py
TrackerGG/Models/Apex/apex_query_data.py
TrackerGG/Models/Apex/apex_segment.py
TrackerGG/Models/Apex/apex_stats.py
TrackerGG/Models/CSGO/__init__.py
TrackerGG/Models/CSGO/csgo_map.py
TrackerGG/Models/CSGO/csgo_map_segment.py
TrackerGG/Models/CSGO/csgo_map_stats.py
TrackerGG/Models/CSGO/csgo_profile.py
TrackerGG/Models/CSGO/csgo_query_data.py
TrackerGG/Models/CSGO/csgo_segment.py
TrackerGG/Models/CSGO/csgo_stats.py
TrackerGG/Models/CSGO/csgo_weapon.py
TrackerGG/Models/CSGO/csgo_weapon_segment.py
TrackerGG/Models/CSGO/csgo_weapon_stats.py
TrackerGG/Models/General/__init__.py
TrackerGG/Models/General/platform.py
TrackerGG/Models/General/platform_info.py
TrackerGG/Models/General/social_account.py
TrackerGG/Models/General/stat.py
TrackerGG/Models/General/user_info.py
TrackerGG-2.7.0.dist-info/LICENSE
TrackerGG-2.7.0.dist-info/METADATA
TrackerGG-2.7.0.dist-info/WHEEL
TrackerGG-2.7.0.dist-info/top_level.txt
TrackerGG-2.7.0.dist-info/RECORD
