Metadata-Version: 2.1
Name: TrackerGG
Version: 2.7.0
Summary: TrackerGG API Wrapper Library
Home-page: https://github.com/dev-ruby/TrackerGG
Author: DevRuby
Author-email: hiveruby@gmail.com
Classifier: Programming Language :: Python
Classifier: License :: OSI Approved :: MIT License
Requires-Python: >=3.7
License-File: LICENSE
Requires-Dist: aiohttp
